glacier_vault.py
setup.py
pyglaciervault.egg-info/PKG-INFO
pyglaciervault.egg-info/SOURCES.txt
pyglaciervault.egg-info/dependency_links.txt
pyglaciervault.egg-info/entry_points.txt
pyglaciervault.egg-info/requires.txt
pyglaciervault.egg-info/top_level.txt