Metadata-Version: 1.0
Name: pyglaciervault
Version: 0.2rc13
Summary: Tool used to remove all archives stored inside an Amazon Glacier vault.
Home-page: https://github.com/rienafairefr/glacier-vault-remove
Author: Leeroy Brun - json streaming from Matthieu Berthomé
Author-email: leeroy.brun@gmail.com -- rienafairefr@gmail.com
License: MIT
Keywords: aws amazon glacier boto archives vaults
Platform: UNKNOWN
